liblta/__init__.py
liblta/_auxiliary.py
liblta/_ethernet.py
liblta/_sseq_handler.py
liblta/legacy_lta.py
liblta/lta_decoder.py
liblta/pylta.py
liblta-3.1.1.dist-info/LICENSE
liblta-3.1.1.dist-info/METADATA
liblta-3.1.1.dist-info/WHEEL
liblta-3.1.1.dist-info/top_level.txt
liblta-3.1.1.dist-info/RECORD
