Metadata-Version: 2.1
Name: liblta
Version: 3.1.1
Summary: A python API to send commands to the LTA (Low-Threshold Acquisition) board.
Author-email: Nicolás Avalos <nicolaseavalos@gmail.com>
Project-URL: Repository, https://gitlab.com/nicolaseavalos/liblta
Classifier: Programming Language :: Python :: 3
Classifier: License :: OSI Approved :: MIT License
Classifier: Topic :: Scientific/Engineering
Requires-Python: >=3.7
License-File: LICENSE
Requires-Dist: numpy
Requires-Dist: pandas
Requires-Dist: astropy
